rl2048player/__init__.py
rl2048player/agents.py
rl2048player/examples.py
rl2048player/game.py
rl2048player/masks.py
rl2048player-0.0.3.dist-info/LICENSE
rl2048player-0.0.3.dist-info/METADATA
rl2048player-0.0.3.dist-info/WHEEL
rl2048player-0.0.3.dist-info/top_level.txt
rl2048player-0.0.3.dist-info/RECORD
